clerkway/__init__.py
clerkway/jwks.py
clerkway/proxy.py
clerkway/py.typed
clerkway-0.1.1.dist-info/METADATA
clerkway-0.1.1.dist-info/WHEEL
clerkway-0.1.1.dist-info/licenses/LICENSE
clerkway-0.1.1.dist-info/RECORD
