Metadata-Version: 2.4
Name: clerkway
Version: 0.1.1
Summary: Clerk authentication proxy for custom domains (ngrok, tunnels, etc.)
Project-URL: Homepage, https://github.com/brYGG-z/clerkway
Project-URL: Documentation, https://github.com/brYGG-z/clerkway#readme
Project-URL: Repository, https://github.com/brYGG-z/clerkway
Author: brYGG-z
License: MIT
License-File: LICENSE
Keywords: authentication,clerk,ngrok,oauth,proxy
Classifier: Development Status :: 4 - Beta
Classifier: Framework :: FastAPI
Classifier: Intended Audience :: Developers
Classifier: License :: OSI Approved :: MIT License
Classifier: Programming Language :: Python :: 3
Classifier: Programming Language :: Python :: 3.10
Classifier: Programming Language :: Python :: 3.11
Classifier: Programming Language :: Python :: 3.12
Classifier: Topic :: Internet :: WWW/HTTP :: HTTP Servers
Classifier: Topic :: Security
Requires-Python: >=3.10
Requires-Dist: fastapi>=0.100.0
Requires-Dist: httpx>=0.25.0
Requires-Dist: pyjwt[crypto]>=2.8.0
Provides-Extra: dev
Requires-Dist: pytest-asyncio>=0.21.0; extra == 'dev'
Requires-Dist: pytest>=7.0.0; extra == 'dev'
Requires-Dist: ruff>=0.1.0; extra == 'dev'
